eolabtools/detection_orientation_culture/orientation_detection.py
eolabtools/detection_orientation_culture/utils.py
eolabtools/night_osm_registration/__init__.py
eolabtools/night_osm_registration/osm_utils.py
eolabtools/night_osm_registration/register_image.py
eolabtools/night_osm_registration/register_vector.py
eolabtools/night_osm_registration/shift.py
eolabtools/sun_map_generation/SunMapGenerator.py
eolabtools-1.0.2.dist-info/licenses/AUTHORS.rst
eolabtools-1.0.2.dist-info/licenses/LICENSE.rst
eolabtools-1.0.2.dist-info/METADATA
eolabtools-1.0.2.dist-info/WHEEL
eolabtools-1.0.2.dist-info/entry_points.txt
eolabtools-1.0.2.dist-info/top_level.txt
eolabtools-1.0.2.dist-info/RECORD
