Metadata-Version: 2.4
Name: eolabtools
Version: 1.0.2
Summary: Collection of tools for data
License:                                  Apache License
Project-URL: homepage, https://github.com/CNES/eolabtools
Project-URL: repository, https://github.com/CNES/eolabtools
Classifier: Programming Language :: Python :: 3
Classifier: Topic :: Scientific/Engineering :: GIS
Classifier: Topic :: Scientific/Engineering :: Image Processing
Classifier: License :: OSI Approved :: Apache Software License
Classifier: Operating System :: OS Independent
Requires-Python: >=3.8.13
License-File: LICENSE.rst
License-File: AUTHORS.rst
Provides-Extra: nightosmreg
Requires-Dist: pytest; extra == "nightosmreg"
Requires-Dist: pytest-cov; extra == "nightosmreg"
Requires-Dist: pyyaml; extra == "nightosmreg"
Requires-Dist: numpy; extra == "nightosmreg"
Requires-Dist: gdal==3.11.0; extra == "nightosmreg"
Requires-Dist: fiona==1.9.6; extra == "nightosmreg"
Requires-Dist: pyogrio; extra == "nightosmreg"
Requires-Dist: shapely>=2; extra == "nightosmreg"
Requires-Dist: geopandas; extra == "nightosmreg"
Requires-Dist: pyrosm; extra == "nightosmreg"
Requires-Dist: rasterio; extra == "nightosmreg"
Requires-Dist: scikit-image; extra == "nightosmreg"
Requires-Dist: opencv-python; extra == "nightosmreg"
Requires-Dist: matplotlib; extra == "nightosmreg"
Provides-Extra: sunmapgen
Requires-Dist: pytest; extra == "sunmapgen"
Requires-Dist: pytest-cov; extra == "sunmapgen"
Requires-Dist: pyyaml; extra == "sunmapgen"
Requires-Dist: gdal==3.5.0; extra == "sunmapgen"
Requires-Dist: numpy<2; extra == "sunmapgen"
Requires-Dist: timezonefinder; extra == "sunmapgen"
Requires-Dist: ephem; extra == "sunmapgen"
Provides-Extra: detecorcult
Requires-Dist: pytest; extra == "detecorcult"
Requires-Dist: pytest-cov; extra == "detecorcult"
Requires-Dist: pyyaml; extra == "detecorcult"
Requires-Dist: geopandas==0.12.2; extra == "detecorcult"
Requires-Dist: fiona==1.9.6; extra == "detecorcult"
Requires-Dist: rasterio; extra == "detecorcult"
Requires-Dist: gdal==3.11.0; extra == "detecorcult"
Requires-Dist: scikit-learn; extra == "detecorcult"
Requires-Dist: opencv-contrib-python; extra == "detecorcult"
Requires-Dist: rasterstats; extra == "detecorcult"
Requires-Dist: numpy==1.26.4; extra == "detecorcult"
Requires-Dist: pandas==1.5.3; extra == "detecorcult"
Dynamic: license-file
